codejamhelpers/__init__.py
codejamhelpers/binary_search.py
codejamhelpers/primes.py
codejamhelpers/probability.py
codejamhelpers-0.1.1.dist-info/DESCRIPTION.rst
codejamhelpers-0.1.1.dist-info/METADATA
codejamhelpers-0.1.1.dist-info/RECORD
codejamhelpers-0.1.1.dist-info/WHEEL
codejamhelpers-0.1.1.dist-info/metadata.json
codejamhelpers-0.1.1.dist-info/top_level.txt
